nvtools/__init__.py
nvtools/io.py
nvtools/plot.py
nvtools/solver.py
nvtools/symmetry.py
nvtools/utils.py
nvtools/vector.py
nvtools/fit/__init__.py
nvtools/fit/odmr.py
nvtools/fit/odmr_model.py
nvtools/fit/utils.py
nvtools-1.0.0.dist-info/LICENSE
nvtools-1.0.0.dist-info/METADATA
nvtools-1.0.0.dist-info/WHEEL
nvtools-1.0.0.dist-info/top_level.txt
nvtools-1.0.0.dist-info/RECORD
