Metadata-Version: 2.1
Name: nvtools
Version: 1.0.0
Summary: Tools for solving the NV center Hamiltonian
Author-email: Dennis Lönard <loenard@rptu.de>
Project-URL: Authors, https://physik.rptu.de/en/wgs/widera/seite
Project-URL: Source, https://gitlab.rlp.net/agwidera/public/nvtools
Project-URL: Documentation, https://agwidera.pages.gitlab.rlp.net/public/nvtools
Classifier: Programming Language :: Python :: 3
Classifier: License :: OSI Approved :: MIT License
Classifier: Operating System :: OS Independent
Requires-Python: >=3.10
License-File: LICENSE
Requires-Dist: numpy >=2.0.0
Requires-Dist: scipy >=1.14.0
Requires-Dist: uncertainties >=3.2.1
Requires-Dist: pint >=0.24.1
Requires-Dist: h5py >=3.11.0
Requires-Dist: prettytable >=3.10.0
Requires-Dist: colorama >=0.4.6
Requires-Dist: matplotlib >=3.9.0
Requires-Dist: setuptools >=70.1.1
